audio2srt/__init__.py
audio2srt/audio2srt.py
autosubtitle/__init__.py
autosubtitle/audio2txt.py
autosubtitle/configs.py
autosubtitle/split_audio.py
autosubtitle/srt.py
autosubtitle/video2audio.py
autosubtitle/write2srt.py
configs/__init__.py
demo/__init__.py
tests/__init__.py
txt2srt/__init__.py
utils/__init__.py
video2audio/__init__.py
video2audio/video2audio.py
AutoSubtitles-0.0.1.dist-info/LICENSE
AutoSubtitles-0.0.1.dist-info/METADATA
AutoSubtitles-0.0.1.dist-info/WHEEL
AutoSubtitles-0.0.1.dist-info/top_level.txt
AutoSubtitles-0.0.1.dist-info/RECORD
