Metadata-Version: 2.1
Name: AutoSubtitles
Version: 0.0.1
Summary: Auto-generates subtitles for any video !
Home-page: https://github.com/yqstar/AutoSubtitles
Author: AndrewYq
Author-email: hfyqstar@163.com
License: UNKNOWN
Platform: UNKNOWN
Classifier: Programming Language :: Python :: 3
Classifier: License :: OSI Approved :: MIT License
Requires-Python: >=3.6
